Metadata-Version: 2.1
Name: chiaki
Version: 0.0.1
Summary: chiaki - chat with a translator
Home-page: https://gitlab.com/nul.one/chiaki
Author: Predrag Mandic
Author-email: predrag@nul.one
License: BSD
Download-URL: https://gitlab.com/nul.one/chiaki/-/archive/0.0.1/chiaki-0.0.1.tar.gz
Platform: UNKNOWN
Classifier: Development Status :: 3 - Alpha
Classifier: Environment :: Console
Classifier: Environment :: Web Environment
Classifier: Intended Audience :: Information Technology
Classifier: Intended Audience :: End Users/Desktop
Classifier: License :: OSI Approved :: BSD License
Classifier: Natural Language :: English
Classifier: Operating System :: POSIX :: Linux
Classifier: Programming Language :: Python :: 3 :: Only
Classifier: Topic :: Communications :: Chat
Requires-Python: >=3.10
